datapipeliner/__init__.py
datapipeliner/datapipeliner.py
datapipeliner/exceptions.py
datapipeliner-0.1.4.dist-info/LICENSE
datapipeliner-0.1.4.dist-info/METADATA
datapipeliner-0.1.4.dist-info/WHEEL
datapipeliner-0.1.4.dist-info/top_level.txt
datapipeliner-0.1.4.dist-info/RECORD
